{
    "result": {
        "id": "UzpfSTE0NzM3NTUyODY2MTI0ODg6Vks6MTQ3Mzc1NTI4NjYxMjQ4OA==",
        "post_id": "1473755286612488",
        "url": "https://www.facebook.com/groups/fbaio/permalink/1473755286612488/",
        "media": {
            "mediaset_token": "pcb.1473755286612488",
            "subAttachments": [
                {
                    "id": "2807673486070900",
                    "url": "https://www.facebook.com/photo.php?fbid=2807673486070900&set=gm.1613099066011442&type=3",
                    "uri": "https://scontent.fsgn2-8.fna.fbcdn.net/v/t39.30808-6/503586015_2880047625500152_2834276911174646514_n.jpg?_nc_cat=102&ccb=1-7&_nc_sid=e06c5d&_nc_ohc=6zjc3768ss0Q7kNvwHbYxxr&_nc_oc=AdoV6tixWBgb8KQsRq5AU0nPJSzLrIFijDyo7UD62qdDTu58UkmiGhkOKr-ugyVNmnM&_nc_zt=23&_nc_ht=scontent.fsgn2-8.fna&_nc_gid=PT1c24i_lr9sJjlVpfIpTg&_nc_ss=7a3a8&oh=00_Af2nG76KbQeyYHkua3pA5gm2Vh1c7leO9rIS20bA8k2YKQ&oe=69E71E5F",
                    "height": 1536,
                    "width": 1024,
                    "accessibility_caption": "Có thể là hình ảnh về văn bản cho biết 'AIO TIÊN ÍCH & MXH ĐINH CAO! TẢI MIỄN PHÍ NGAY BULK QUẢNLÝ DOWNLOADER STORY XUẤT TIN NHẦN LƯU BÀIVIẾT BÀI VIẾT LOC BẠN BÈ QUẢN LÝ CHẶN QUẢN LÝ CHẬN Βό EO DÔI Xem hình minh họạ để biết từng chức nãng chiết!'",
                    "real_width": 1024,
                    "real_height": 1536
                },
                {
                    "id": "2888776637960584",
                    "url": "https://www.facebook.com/photo.php?fbid=2888776637960584&set=gm.1667483947239620&type=3",
                    "uri": "https://scontent.fsgn2-4.fna.fbcdn.net/v/t39.30808-6/508408784_2888776641293917_3531185380193432250_n.jpg?_nc_cat=101&ccb=1-7&_nc_sid=e06c5d&_nc_ohc=mZo0Pc33ZK0Q7kNvwFjEjqT&_nc_oc=Adp_j6Ov8BXDigpV6BuHRPFpFiEGIhFJ6FcfNetYow9mCRjcbOzhkthzDpDLcpxGvRU&_nc_zt=23&_nc_ht=scontent.fsgn2-4.fna&_nc_gid=PT1c24i_lr9sJjlVpfIpTg&_nc_ss=7a3a8&oh=00_Af0ZNiXG-tXTknsv_nITNgJ3AR1rjR9a6OJjS7XcSJNBSA&oe=69E71FE7",
                    "height": 734,
                    "width": 1108,
                    "accessibility_caption": "Không có mô tả ảnh.",
                    "real_width": 1108,
                    "real_height": 734
                },
                {
                    "id": "2722894181215498",
                    "url": "https://www.facebook.com/photo.php?fbid=2722894181215498&set=gm.1547981292523220&type=3",
                    "uri": "https://scontent.fsgn2-5.fna.fbcdn.net/v/t39.30808-6/504313730_2879337382237843_6550830541429589241_n.jpg?_nc_cat=111&ccb=1-7&_nc_sid=e06c5d&_nc_ohc=i5FkUtEYZQMQ7kNvwFc5NwD&_nc_oc=Adp_cxctpvKmnbYxlsmiIH8EzzstmHEY9zKSQaIt-G0TkEU7epj3NZIFB7s5rK1pzb8&_nc_zt=23&_nc_ht=scontent.fsgn2-5.fna&_nc_gid=PT1c24i_lr9sJjlVpfIpTg&_nc_ss=7a3a8&oh=00_Af3m0nY1aKiPmI3wROKxLBHeXOwFxbj7J8k9jwTPeWs22A&oe=69E72616",
                    "height": 897,
                    "width": 1253,
                    "accessibility_caption": "Có thể là hình ảnh về văn bản",
                    "real_width": 1253,
                    "real_height": 897
                },
                {
                    "id": "2722898437881739",
                    "url": "https://www.facebook.com/photo.php?fbid=2722898437881739&set=gm.1547981319189884&type=3",
                    "uri": "https://scontent.fsgn2-10.fna.fbcdn.net/v/t39.30808-6/503920984_2879337632237818_8475799531092182418_n.jpg?_nc_cat=109&ccb=1-7&_nc_sid=e06c5d&_nc_ohc=CWO-u65pEcsQ7kNvwHrv7fx&_nc_oc=AdqD2UWhXxQ8u7jdpnBd6cE6r5opK_0iZfZ9y2B0n7pX1wJMPOSCWeLHNx2BeAGf52w&_nc_zt=23&_nc_ht=scontent.fsgn2-10.fna&_nc_gid=PT1c24i_lr9sJjlVpfIpTg&_nc_ss=7a3a8&oh=00_Af23l5vNhVHXqRP8Lwiqc4pvMknDwyHOWl7aaJwd3W-3aQ&oe=69E730DA",
                    "height": 901,
                    "width": 1363,
                    "accessibility_caption": "Có thể là hình ảnh về ‎2 người, điện thoại và ‎văn bản cho biết '‎F Trangchi làng Tin oạt Hot ® Khám Hômnay 0 Kho Kholuutru utrữ Tin (Story) Hoang Tran 100004848287494 日 Reels Mii 1 Tinnhắn รู Xemt xenttibme bạn danh Bạn ès sẽ hông biết ạn ดลี xem cùa họ c Làmm ا ล่น tiên tát cả Facebook Mới Mới Thu ổi cảm Tiệnich 1 Trogiúp 사형민 Faceboak One 2024 Cretead‎'‎‎",
                    "real_width": 1363,
                    "real_height": 901
                },
                {
                    "id": "2722899834548266",
                    "url": "https://www.facebook.com/photo.php?fbid=2722899834548266&set=gm.1547981312523218&type=3",
                    "uri": "https://scontent.fsgn2-3.fna.fbcdn.net/v/t39.30808-6/504516870_2879337518904496_6616910794972725780_n.jpg?_nc_cat=107&ccb=1-7&_nc_sid=e06c5d&_nc_ohc=2HYhra6EhNoQ7kNvwGW1fb8&_nc_oc=AdpnbuP8-hvX-lZNJTxrIXkDnPMmZ3_pHz5gZ2K8dWHnXYbA1zoBFkiUmHAvpg2uPUQ&_nc_zt=23&_nc_ht=scontent.fsgn2-3.fna&_nc_gid=PT1c24i_lr9sJjlVpfIpTg&_nc_ss=7a3a8&oh=00_Af3uC8DzILWYM_b8-S71XOPXUg0FXLwGtcw7rk9e8C_h3Q&oe=69E72B2D",
                    "height": 901,
                    "width": 1046,
                    "accessibility_caption": "Có thể là hình ảnh về 3 người và văn bản",
                    "real_width": 1046,
                    "real_height": 901
                }
            ],
            "photo": null,
            "video": null
        },
        "text": "# 🚀 **FB AIO – Tiện ích đỉnh cao dành cho Phở bò & MXH!**\n\n🧰 Tất cả công cụ **hay ho nhất** gom gọn trong **1 tiện ích duy nhất**!\n📥 **TẢI MIỄN PHÍ NGAY**: [https://j2c.cc/fb-aio-webstore](https://j2c.cc/fb-aio-webstore)\n\n🌐 Hỗ trợ: **Phở bò | IG | Threads | Tíc tóc | Gu gồ**\n🎯 Giao diện dễ xài – Dùng là ghiền – Không cần biết kỹ thuật!\n\n💎 **TOP TÍNH NĂNG XỊN NHẤT**:\n* 📥 **Bulk Downloader** – Tải hàng loạt cực nhanh\n* 📖 **Story Manager** – Quản lý + lưu story tiện lợi\n* 💬 **Tin nhắn** – Xuất & backup chỉ vài click\n* 📜 **Bài viết** – Lưu, Xoá, Sửa quyền riêng tư hàng loạt\n* 👥 **Bạn bè** – Dọn dẹp, sàng lọc bạn nhanh chóng\n* 👤 **Lời mời kết bạn** – Lọc sạch, duyệt siêu tốc\n* 🚫 **Danh sách chặn** – Quản lý rõ ràng\n* 👁 **Đang theo dõi** – Bỏ theo dõi 1 nốt nhạc\n* ⚙️ Và nhiều tiện ích xịn khác đang chờ bạn khám phá!\n\n📸 Xem hình minh hoạ để biết từng chức năng chi tiết!\n🎁 **HIỆN ĐANG FREE** – Sài sớm kẻo tiếc nha!\n👯‍♂️ Tag hội bạn hay dùng Facebook cùng thử nhé!\n\n#fb_aio #tienich #facebooktips #bulkdownloader #musthave",
        "text_format": {},
        "rich_message": [
            {
                "__typename": "ComposedHeaderOneBlockWithEntities",
                "__isComposedBlockWithEntities": "ComposedHeaderOneBlockWithEntities",
                "block_type": "HEADER_ONE",
                "data": "{}",
                "depth": 0,
                "media_alignment": null,
                "media_caption": null,
                "entity_ranges": [],
                "inline_style_ranges": [
                    {
                        "inline_style": "BOLD",
                        "length": 49,
                        "offset": 2
                    }
                ],
                "text": "🚀 FB AIO – Tiện ích đỉnh cao dành cho Phở bò & MXH!"
            },
            {
                "__typename": "ComposedUnstyledBlockWithEntities",
                "__isComposedBlockWithEntities": "ComposedUnstyledBlockWithEntities",
                "block_type": "UNSTYLED",
                "data": "{}",
                "depth": 0,
                "media_alignment": null,
                "media_caption": null,
                "entity_ranges": [],
                "inline_style_ranges": [],
                "text": ""
            },
            {
                "__typename": "ComposedUnstyledBlockWithEntities",
                "__isComposedBlockWithEntities": "ComposedUnstyledBlockWithEntities",
                "block_type": "UNSTYLED",
                "data": "{}",
                "depth": 0,
                "media_alignment": null,
                "media_caption": null,
                "entity_ranges": [],
                "inline_style_ranges": [
                    {
                        "inline_style": "BOLD",
                        "length": 11,
                        "offset": 17
                    },
                    {
                        "inline_style": "BOLD",
                        "length": 19,
                        "offset": 43
                    },
                    {
                        "inline_style": "BOLD",
                        "length": 17,
                        "offset": 66
                    }
                ],
                "text": "🧰 Tất cả công cụ hay ho nhất gom gọn trong 1 tiện ích duy nhất!\n📥 TẢI MIỄN PHÍ NGAY: https://j2c.cc/fb-aio-webstore"
            },
            {
                "__typename": "ComposedUnstyledBlockWithEntities",
                "__isComposedBlockWithEntities": "ComposedUnstyledBlockWithEntities",
                "block_type": "UNSTYLED",
                "data": "{}",
                "depth": 0,
                "media_alignment": null,
                "media_caption": null,
                "entity_ranges": [],
                "inline_style_ranges": [
                    {
                        "inline_style": "BOLD",
                        "length": 39,
                        "offset": 10
                    }
                ],
                "text": "🌐 Hỗ trợ: Phở bò | IG | Threads | Tíc tóc | Gu gồ\n🎯 Giao diện dễ xài – Dùng là ghiền – Không cần biết kỹ thuật!"
            },
            {
                "__typename": "ComposedUnstyledBlockWithEntities",
                "__isComposedBlockWithEntities": "ComposedUnstyledBlockWithEntities",
                "block_type": "UNSTYLED",
                "data": "{}",
                "depth": 0,
                "media_alignment": null,
                "media_caption": null,
                "entity_ranges": [],
                "inline_style_ranges": [],
                "text": ""
            },
            {
                "__typename": "ComposedUnstyledBlockWithEntities",
                "__isComposedBlockWithEntities": "ComposedUnstyledBlockWithEntities",
                "block_type": "UNSTYLED",
                "data": "{}",
                "depth": 0,
                "media_alignment": null,
                "media_caption": null,
                "entity_ranges": [],
                "inline_style_ranges": [
                    {
                        "inline_style": "BOLD",
                        "length": 22,
                        "offset": 2
                    }
                ],
                "text": "💎 TOP TÍNH NĂNG XỊN NHẤT:"
            },
            {
                "__typename": "ComposedUnorderedListItemBlockWithEntities",
                "__isComposedBlockWithEntities": "ComposedUnorderedListItemBlockWithEntities",
                "block_type": "UNORDERED_LIST_ITEM",
                "data": "{}",
                "depth": 0,
                "media_alignment": null,
                "media_caption": null,
                "entity_ranges": [],
                "inline_style_ranges": [
                    {
                        "inline_style": "BOLD",
                        "length": 15,
                        "offset": 2
                    }
                ],
                "text": "📥 Bulk Downloader – Tải hàng loạt cực nhanh"
            },
            {
                "__typename": "ComposedUnorderedListItemBlockWithEntities",
                "__isComposedBlockWithEntities": "ComposedUnorderedListItemBlockWithEntities",
                "block_type": "UNORDERED_LIST_ITEM",
                "data": "{}",
                "depth": 0,
                "media_alignment": null,
                "media_caption": null,
                "entity_ranges": [],
                "inline_style_ranges": [
                    {
                        "inline_style": "BOLD",
                        "length": 13,
                        "offset": 2
                    }
                ],
                "text": "📖 Story Manager – Quản lý + lưu story tiện lợi"
            },
            {
                "__typename": "ComposedUnorderedListItemBlockWithEntities",
                "__isComposedBlockWithEntities": "ComposedUnorderedListItemBlockWithEntities",
                "block_type": "UNORDERED_LIST_ITEM",
                "data": "{}",
                "depth": 0,
                "media_alignment": null,
                "media_caption": null,
                "entity_ranges": [],
                "inline_style_ranges": [
                    {
                        "inline_style": "BOLD",
                        "length": 8,
                        "offset": 2
                    }
                ],
                "text": "💬 Tin nhắn – Xuất & backup chỉ vài click"
            },
            {
                "__typename": "ComposedUnorderedListItemBlockWithEntities",
                "__isComposedBlockWithEntities": "ComposedUnorderedListItemBlockWithEntities",
                "block_type": "UNORDERED_LIST_ITEM",
                "data": "{}",
                "depth": 0,
                "media_alignment": null,
                "media_caption": null,
                "entity_ranges": [],
                "inline_style_ranges": [
                    {
                        "inline_style": "BOLD",
                        "length": 8,
                        "offset": 2
                    }
                ],
                "text": "📜 Bài viết – Lưu, Xoá, Sửa quyền riêng tư hàng loạt"
            },
            {
                "__typename": "ComposedUnorderedListItemBlockWithEntities",
                "__isComposedBlockWithEntities": "ComposedUnorderedListItemBlockWithEntities",
                "block_type": "UNORDERED_LIST_ITEM",
                "data": "{}",
                "depth": 0,
                "media_alignment": null,
                "media_caption": null,
                "entity_ranges": [],
                "inline_style_ranges": [
                    {
                        "inline_style": "BOLD",
                        "length": 6,
                        "offset": 2
                    }
                ],
                "text": "👥 Bạn bè – Dọn dẹp, sàng lọc bạn nhanh chóng"
            },
            {
                "__typename": "ComposedUnorderedListItemBlockWithEntities",
                "__isComposedBlockWithEntities": "ComposedUnorderedListItemBlockWithEntities",
                "block_type": "UNORDERED_LIST_ITEM",
                "data": "{}",
                "depth": 0,
                "media_alignment": null,
                "media_caption": null,
                "entity_ranges": [],
                "inline_style_ranges": [
                    {
                        "inline_style": "BOLD",
                        "length": 15,
                        "offset": 2
                    }
                ],
                "text": "👤 Lời mời kết bạn – Lọc sạch, duyệt siêu tốc"
            },
            {
                "__typename": "ComposedUnorderedListItemBlockWithEntities",
                "__isComposedBlockWithEntities": "ComposedUnorderedListItemBlockWithEntities",
                "block_type": "UNORDERED_LIST_ITEM",
                "data": "{}",
                "depth": 0,
                "media_alignment": null,
                "media_caption": null,
                "entity_ranges": [],
                "inline_style_ranges": [
                    {
                        "inline_style": "BOLD",
                        "length": 14,
                        "offset": 2
                    }
                ],
                "text": "🚫 Danh sách chặn – Quản lý rõ ràng"
            },
            {
                "__typename": "ComposedUnorderedListItemBlockWithEntities",
                "__isComposedBlockWithEntities": "ComposedUnorderedListItemBlockWithEntities",
                "block_type": "UNORDERED_LIST_ITEM",
                "data": "{}",
                "depth": 0,
                "media_alignment": null,
                "media_caption": null,
                "entity_ranges": [],
                "inline_style_ranges": [
                    {
                        "inline_style": "BOLD",
                        "length": 13,
                        "offset": 2
                    }
                ],
                "text": "👁 Đang theo dõi – Bỏ theo dõi 1 nốt nhạc"
            },
            {
                "__typename": "ComposedUnorderedListItemBlockWithEntities",
                "__isComposedBlockWithEntities": "ComposedUnorderedListItemBlockWithEntities",
                "block_type": "UNORDERED_LIST_ITEM",
                "data": "{}",
                "depth": 0,
                "media_alignment": null,
                "media_caption": null,
                "entity_ranges": [],
                "inline_style_ranges": [],
                "text": "⚙️ Và nhiều tiện ích xịn khác đang chờ bạn khám phá!"
            },
            {
                "__typename": "ComposedUnstyledBlockWithEntities",
                "__isComposedBlockWithEntities": "ComposedUnstyledBlockWithEntities",
                "block_type": "UNSTYLED",
                "data": "{}",
                "depth": 0,
                "media_alignment": null,
                "media_caption": null,
                "entity_ranges": [],
                "inline_style_ranges": [],
                "text": ""
            },
            {
                "__typename": "ComposedUnstyledBlockWithEntities",
                "__isComposedBlockWithEntities": "ComposedUnstyledBlockWithEntities",
                "block_type": "UNSTYLED",
                "data": "{}",
                "depth": 0,
                "media_alignment": null,
                "media_caption": null,
                "entity_ranges": [],
                "inline_style_ranges": [
                    {
                        "inline_style": "BOLD",
                        "length": 14,
                        "offset": 55
                    }
                ],
                "text": "📸 Xem hình minh hoạ để biết từng chức năng chi tiết!\n🎁 HIỆN ĐANG FREE – Sài sớm kẻo tiếc nha!\n👯‍♂️ Tag hội bạn hay dùng Facebook cùng thử nhé!"
            },
            {
                "__typename": "ComposedUnstyledBlockWithEntities",
                "__isComposedBlockWithEntities": "ComposedUnstyledBlockWithEntities",
                "block_type": "UNSTYLED",
                "data": "{}",
                "depth": 0,
                "media_alignment": null,
                "media_caption": null,
                "entity_ranges": [],
                "inline_style_ranges": [],
                "text": ""
            },
            {
                "__typename": "ComposedUnstyledBlockWithEntities",
                "__isComposedBlockWithEntities": "ComposedUnstyledBlockWithEntities",
                "block_type": "UNSTYLED",
                "data": "{}",
                "depth": 0,
                "media_alignment": null,
                "media_caption": null,
                "entity_ranges": [
                    {
                        "entity_type": "HASHTAG",
                        "entity": {
                            "__typename": "Hashtag",
                            "__isEntity": "Hashtag",
                            "url": "https://www.facebook.com/hashtag/fb_aio",
                            "mobileUrl": "https://m.facebook.com/hashtag/fb_aio",
                            "__isNode": "Hashtag",
                            "id": "8080904801977702"
                        },
                        "length": 7,
                        "offset": 0
                    },
                    {
                        "entity_type": "HASHTAG",
                        "entity": {
                            "__typename": "Hashtag",
                            "__isEntity": "Hashtag",
                            "url": "https://www.facebook.com/hashtag/tienich",
                            "mobileUrl": "https://m.facebook.com/hashtag/tienich",
                            "__isNode": "Hashtag",
                            "id": "405235412914027"
                        },
                        "length": 8,
                        "offset": 8
                    },
                    {
                        "entity_type": "HASHTAG",
                        "entity": {
                            "__typename": "Hashtag",
                            "__isEntity": "Hashtag",
                            "url": "https://www.facebook.com/hashtag/facebooktips",
                            "mobileUrl": "https://m.facebook.com/hashtag/facebooktips",
                            "__isNode": "Hashtag",
                            "id": "445916488822399"
                        },
                        "length": 13,
                        "offset": 17
                    },
                    {
                        "entity_type": "HASHTAG",
                        "entity": {
                            "__typename": "Hashtag",
                            "__isEntity": "Hashtag",
                            "url": "https://www.facebook.com/hashtag/bulkdownloader",
                            "mobileUrl": "https://m.facebook.com/hashtag/bulkdownloader",
                            "__isNode": "Hashtag",
                            "id": "783877798353440"
                        },
                        "length": 15,
                        "offset": 31
                    },
                    {
                        "entity_type": "HASHTAG",
                        "entity": {
                            "__typename": "Hashtag",
                            "__isEntity": "Hashtag",
                            "url": "https://www.facebook.com/hashtag/musthave",
                            "mobileUrl": "https://m.facebook.com/hashtag/musthave",
                            "__isNode": "Hashtag",
                            "id": "583049568373504"
                        },
                        "length": 9,
                        "offset": 47
                    }
                ],
                "inline_style_ranges": [],
                "text": "#fb_aio #tienich #facebooktips #bulkdownloader #musthave"
            }
        ],
        "hashtags": [
            "#fb_aio",
            "#tienich",
            "#facebooktips",
            "#bulkdownloader",
            "#musthave"
        ],
        "mentions": [],
        "actors": [
            {
                "__typename": "User",
                "id": "100004848287494",
                "name": "Hoang Tran",
                "__isEntity": "User",
                "url": "https://www.facebook.com/9999.hoangtran"
            }
        ],
        "comments": {
            "can_comment": false,
            "total": 124,
            "total_count": 184,
            "sorting": {
                "selected": {
                    "title": "Tất cả bình luận",
                    "description": "Hiển thị tất cả bình luận, bao gồm cả nội dung có thể là spam.",
                    "intent_token": "CHRONOLOGICAL_UNFILTERED_INTENT_V1"
                },
                "available": [
                    {
                        "title": "Tất cả bình luận",
                        "description": "Hiển thị tất cả bình luận, bao gồm cả nội dung có thể là spam.",
                        "intent_token": "CHRONOLOGICAL_UNFILTERED_INTENT_V1"
                    },
                    {
                        "title": "Phù hợp nhất",
                        "description": "Hiển thị bình luận của bạn bè và những bình luận có nhiều lượt tương tác nhất trước tiên.",
                        "intent_token": "RANKED_FILTERED_INTENT_V1"
                    },
                    {
                        "title": "Mới nhất",
                        "description": "Hiển thị tất cả bình luận, mới nhất trước tiên.",
                        "intent_token": "REVERSE_CHRONOLOGICAL_UNFILTERED_INTENT_V1"
                    }
                ]
            }
        },
        "reactions": {
            "my": "1635855486666999",
            "total": 2948,
            "top": [
                {
                    "id": "1635855486666999",
                    "count": 2860,
                    "name": "Thích"
                },
                {
                    "id": "1678524932434102",
                    "count": 84,
                    "name": "Yêu thích"
                },
                {
                    "id": "613557422527858",
                    "count": 2,
                    "name": "Thương thương"
                },
                {
                    "id": "115940658764963",
                    "count": 1,
                    "name": "Haha"
                },
                {
                    "id": "908563459236466",
                    "count": 1,
                    "name": "Buồn"
                }
            ]
        },
        "shares": 4116,
        "created_time": 1724749596000,
        "privacy_scope": "Nhóm công khai",
        "copyright_violation_header": null,
        "tracking_ids": {
            "top_level_post_id": "1473755286612488",
            "content_owner_id_new": "100004848287494",
            "photo_attachments_list": [
                "2807673486070900",
                "2888776637960584",
                "2722894181215498",
                "2722898437881739",
                "2722899834548266"
            ],
            "photo_id": "2807673486070900",
            "story_location": 9,
            "story_attachment_style": "album",
            "ent_attachement_type": "PhotoSetAttachment",
            "page_insights": {
                "1154059318582088": {
                    "page_id": "1154059318582088",
                    "page_id_type": "group",
                    "actor_id": "100004848287494",
                    "dm": {
                        "isShare": 0,
                        "originalPostOwnerID": 0,
                        "sharedMediaID": 0,
                        "sharedMediaOwnerID": 0
                    },
                    "psn": "EntGroupMallPostCreationStory",
                    "post_context": {
                        "object_fbtype": 657,
                        "publish_time": 1724749596,
                        "story_name": "EntGroupMallPostCreationStory",
                        "story_fbid": [
                            "1473755286612488"
                        ]
                    },
                    "role": 1,
                    "sl": 9
                }
            },
            "profile_id": "100004848287494",
            "actrs": "100004848287494",
            "tds_flgs": 3
        },
        "posted_to": {
            "type": "Group",
            "id": "1154059318582088",
            "url": "https://www.facebook.com/groups/fbaio/",
            "name": "FB AIO Extension",
            "avatar": "https://scontent.fsgn2-4.fna.fbcdn.net/v/t39.30808-6/565663532_801114855981820_4333487968731823947_n.png?stp=c394.0.428.428a_cp6_dst-png_s110x80&_nc_cat=101&ccb=1-7&_nc_sid=a9d32b&_nc_ohc=EnSdNHQrpIkQ7kNvwGk6jW-&_nc_oc=AdrCtmHSrCltToxGynBFzoEgNbXezbLaA3P7xYDCtpiKusjr2S8gIVZWmt6ArHw5_Xw&_nc_zt=23&_nc_ht=scontent.fsgn2-4.fna&_nc_gid=PT1c24i_lr9sJjlVpfIpTg&_nc_ss=7a3a8&oh=00_Af3MKm0P3vboVB6wkMkg2FkyEvogfaaDMbmU9tlpt0BG5A&oe=69E73DB6"
        },
        "attached_post": null
    }
}
